{
  "image_id": "31fcc94f3079f2b234c6e4304ab540e3",
  "split": "train",
  "birads": "BI-RADS 4",
  "lesions": [
    {
      "type": "Mass",
      "class_id": 0,
      "category": "Mass",
      "birads": "BI-RADS 4",
      "bbox_original": {
        "xmin": 153.05700683594,
        "ymin": 1941.9799804688,
        "xmax": 342.67401123047,
        "ymax": 2161.6201171875
      },
      "bbox_normalized": {
        "x_center": 0.08852339608328749,
        "y_center": 0.5832291213269329,
        "width": 0.06772035871233215,
        "height": 0.0624332395448266
      }
    }
  ]
}